AUTHORS.rst
CONTRIBUTING.rst
HISTORY.rst
LICENSE
MANIFEST.in
README.rst
setup.py
facehugger/__init__.py
facehugger/facehugger.py
facehugger/haarcascade_frontalface_alt.xml
facehugger/haarcascade_frontalface_alt2.xml
facehugger/haarcascade_frontalface_alt_tree.xml
facehugger/utils.py
facehugger.egg-info/PKG-INFO
facehugger.egg-info/SOURCES.txt
facehugger.egg-info/dependency_links.txt
facehugger.egg-info/entry_points.txt
facehugger.egg-info/not-zip-safe
facehugger.egg-info/requires.txt
facehugger.egg-info/top_level.txt