Metadata-Version: 1.1
Name: facehugger
Version: 0.1.6
Summary: Extracts faces from an image
Home-page: https://github.com/dnmellen/facehugger
Author: Diego Navarro Mellen
Author-email: dnmellen@gmail.com
License: BSD
Keywords: facehugger,simplecv,vision,face,crawl
Platform: UNKNOWN
Classifier: Development Status :: 2 - Pre-Alpha
Classifier: Intended Audience :: Developers
Classifier: Intended Audience :: Science/Research
Classifier: Intended Audience :: Education
Classifier: Intended Audience :: End Users/Desktop
Classifier: License :: OSI Approved :: BSD License
Classifier: Natural Language :: English
Classifier: Topic :: Scientific/Engineering :: Image Recognition
Classifier: Topic :: Utilities
Classifier: Programming Language :: Python :: 2
Classifier: Programming Language :: Python :: 2.7
